{"country": "BJ", "regions": [{"region": "Littoral", "count": 1484}, {"region": "Atlantique", "count": 159}, {"region": "Collines", "count": 22}, {"region": "Borgou", "count": 15}, {"region": "Mono", "count": 13}, {"region": "Alibori", "count": 11}, {"region": "Plateau", "count": 10}, {"region": "Atakora", "count": 7}, {"region": "Ou\u00e9m\u00e9", "count": 7}, {"region": "Kouffo", "count": 5}, {"region": "Zou", "count": 3}, {"region": "Donga", "count": 1}], "encryption": [{"wep": "2", "count": 1135}, {"wep": "?", "count": 443}, {"wep": "Y", "count": 76}, {"wep": "W", "count": 72}, {"wep": "N", "count": 12}], "success": true, "postalCode": [{"postalCode": "08 BP 0929", "count": 911}, {"postalCode": "01 BP 7053", "count": 165}, {"postalCode": "01", "count": 144}, {"postalCode": "163", "count": 116}, {"postalCode": "08BP0089 TRI POSTAL", "count": 107}, {"postalCode": "09BP529", "count": 94}, {"postalCode": "01BP:1086 Cotonou", "count": 28}, {"postalCode": "B.P. 428 LOKOSSA", "count": 4}, {"postalCode": "0123", "count": 3}, {"postalCode": "05BP1063 COTONOU- BENIN", "count": 3}, {"postalCode": "07 BP 284", "count": 3}, {"postalCode": "05BP:301 Cotonou", "count": 2}, {"postalCode": "BP: 1564 Abomey-Calavi", "count": 2}, {"postalCode": "03BP647", "count": 1}, {"postalCode": "01 BP 504", "count": 1}]}